atxweb/server.py
atxweb/__init__.py
atxweb/__main__.py
atxweb/static/favicon.png
atxweb/static/index.html
atxweb/static/blockly/blockly_compressed.js
atxweb/static/blockly/blocks_compressed.js
atxweb/static/blockly/python_compressed.js
atxweb/static/blockly/media/1x1.gif
atxweb/static/blockly/media/accessible.css
atxweb/static/blockly/media/atx-phone.png
atxweb/static/blockly/media/click.mp3
atxweb/static/blockly/media/click.ogg
atxweb/static/blockly/media/click.wav
atxweb/static/blockly/media/delete.mp3
atxweb/static/blockly/media/delete.ogg
atxweb/static/blockly/media/delete.wav
atxweb/static/blockly/media/disconnect.mp3
atxweb/static/blockly/media/disconnect.ogg
atxweb/static/blockly/media/disconnect.wav
atxweb/static/blockly/media/handclosed.cur
atxweb/static/blockly/media/handdelete.cur
atxweb/static/blockly/media/handopen.cur
atxweb/static/blockly/media/quote0.png
atxweb/static/blockly/media/quote1.png
atxweb/static/blockly/media/sprites.png
atxweb/static/blockly/media/sprites.svg
atxweb/static/blockly/msg/js/en.js
atxweb/static/css/bootstrap-3.3.5.min.css
atxweb/static/css/index.css
atxweb/static/css/jquery.fancybox.min.css
atxweb/static/fonts/glyphicons-halflings-regular.ttf
atxweb/static/fonts/glyphicons-halflings-regular.woff
atxweb/static/fonts/glyphicons-halflings-regular.woff2
atxweb/static/icons/back.ico
atxweb/static/icons/exit.ico
atxweb/static/icons/home.ico
atxweb/static/icons/menu.ico
atxweb/static/icons/power.ico
atxweb/static/icons/rotate.ico
atxweb/static/icons/rotate2.ico
atxweb/static/icons/save.ico
atxweb/static/icons/volume_down.ico
atxweb/static/icons/volume_up.ico
atxweb/static/js/bootstrap-3.3.5.min.js
atxweb/static/js/index.js
atxweb/static/js/jquery-1.11.3.min.js
atxweb/static/js/jquery.fancybox.pack.js
atxweb/static/js/jquery.mousewheel.min.js
atxweb/static/js/notify.js
atxweb/static/js/vue.js
atxweb/static/js/vue.min.js
atx_webide-0.0.2.dist-info/DESCRIPTION.rst
atx_webide-0.0.2.dist-info/METADATA
atx_webide-0.0.2.dist-info/metadata.json
atx_webide-0.0.2.dist-info/pbr.json
atx_webide-0.0.2.dist-info/RECORD
atx_webide-0.0.2.dist-info/top_level.txt
atx_webide-0.0.2.dist-info/WHEEL
