Metadata-Version: 2.0
Name: atx-webide
Version: 0.0.2
Summary: Helper tool for writing atx testcase using google blockly.
Home-page: https://github.com/openatx/atx-webide
Author: wuxc
Author-email: wuxc08@gmail.com
License: Apache
Platform: UNKNOWN
Classifier: Environment :: Console
Classifier: Intended Audience :: Developers
Classifier: Operating System :: OS Independent
Classifier: Programming Language :: Python :: 2.7
Requires-Dist: atx (>=1.0.13)
Requires-Dist: tornado (==4.3)
Requires-Dist: futures (==3.0.5)
